rtl/register_file.v
module register_file(

    input clk,
    input we,

    input [4:0] rs1,
    input [4:0] rs2,
    input [4:0] rd,

    input [31:0] write_data,

    output [31:0] read_data1,
    output [31:0] read_data2

);
    // 32 registers, each 32 bits wide
    reg [31:0] registers [0:31];

    integer i;

    // Initialize all registers to zero
    initial begin
        for(i = 0; i < 32; i = i + 1)
            registers[i] = 32'd0;
    end

    // Read ports (combinational)
    assign read_data1 = registers[rs1];
    assign read_data2 = registers[rs2];

    // Write port (sequential)
    always @(posedge clk) begin
        if(we && rd != 0)
            registers[rd] <= write_data;
    end

endmodule

rtl/control_unit.v
module control_unit(

    input [6:0] opcode,

    output reg RegWrite,
    output reg MemRead,
    output reg MemWrite,
    output reg ALUSrc,
    output reg MemtoReg,
    output reg [1:0] ALUOp

);

always @(*) begin

    // Default values
    RegWrite = 0;
    MemRead = 0;
    MemWrite = 0;
    ALUSrc = 0;
    MemtoReg = 0;
    ALUOp = 2'b00;

    case(opcode)

        // R-Type Instructions
        7'b0110011: begin
            RegWrite = 1;
            ALUSrc = 0;
            MemRead = 0;
            MemWrite = 0;
            MemtoReg = 0;
            ALUOp = 2'b10;
        end

        // Load (LW)
        7'b0000011: begin
            RegWrite = 1;
            ALUSrc = 1;
            MemRead = 1;
            MemWrite = 0;
            MemtoReg = 1;
            ALUOp = 2'b00;
        end

        // Store (SW)
        7'b0100011: begin
            RegWrite = 0;
            ALUSrc = 1;
            MemRead = 0;
            MemWrite = 1;
            MemtoReg = 0;
            ALUOp = 2'b00;
        end

        // Branch (BEQ)
        7'b1100011: begin
            RegWrite = 0;
            ALUSrc = 0;
            MemRead = 0;
            MemWrite = 0;
            MemtoReg = 0;
            ALUOp = 2'b01;
        end

    endcase

end

endmodule

rtl/if_id.v
module if_id(

    input clk,
    input reset,

    input [31:0] pc_in,
    input [31:0] instruction_in,

    output reg [31:0] pc_out,
    output reg [31:0] instruction_out

);

always @(posedge clk or posedge reset) begin

    if(reset) begin
        pc_out <= 32'd0;
        instruction_out <= 32'd0;
    end
    else begin
        pc_out <= pc_in;
        instruction_out <= instruction_in;
    end

end

endmodule

rtl/instruction_memory.v
module instruction_memory(
    input [31:0] address,
    output [31:0] instruction
);

    // Memory of 256 instructions
    reg [31:0] memory [0:255];

    // Initialize memory
    initial begin

        // add x3, x1, x2
        memory[0] = 32'h002081B3;

        // sub x4, x3, x1
        memory[1] = 32'h40118233;

        // and x5, x3, x4
        memory[2] = 32'h0041F2B3;

        // or x6, x5, x2
        memory[3] = 32'h0022E333;

    end

    // Address is byte address, so divide by 4
    assign instruction = memory[address[31:2]];

endmodule

rtl/pc.v
module pc(
    input clk,
    input reset,
    input [31:0] pc_next,
    output reg [31:0] pc
);

always @(posedge clk or posedge reset)
begin
    if(reset)
        pc <= 32'd0;
    else
        pc <= pc_next;
end

endmodule

rtl/pipeline_processor.v
module pipeline_processor(

    input clk,
    input reset

);

//=========================
// IF Stage
//=========================

wire [31:0] pc;
wire [31:0] pc_next;
wire [31:0] instruction;

assign pc_next = pc + 4;

pc PC(
    .clk(clk),
    .reset(reset),
    .pc_next(pc_next),
    .pc(pc)
);

instruction_memory IM(
    .address(pc),
    .instruction(instruction)
);

//=========================
// IF/ID Register
//=========================

wire [31:0] ifid_pc;
wire [31:0] ifid_instruction;

if_id IF_ID(

    .clk(clk),
    .reset(reset),

    .pc_in(pc),
    .instruction_in(instruction),

    .pc_out(ifid_pc),
    .instruction_out(ifid_instruction)

);

//=========================
// Control Unit
//=========================

wire RegWrite;
wire MemRead;
wire MemWrite;
wire ALUSrc;
wire MemtoReg;
wire [1:0] ALUOp;

control_unit CU(

    .opcode(ifid_instruction[6:0]),

    .RegWrite(RegWrite),
    .MemRead(MemRead),
    .MemWrite(MemWrite),
    .ALUSrc(ALUSrc),
    .MemtoReg(MemtoReg),
    .ALUOp(ALUOp)

);

//=========================
// Register File
//=========================

wire [31:0] read_data1;
wire [31:0] read_data2;

register_file RF(

    .clk(clk),
    .we(1'b0),

    .rs1(ifid_instruction[19:15]),
    .rs2(ifid_instruction[24:20]),
    .rd(5'd0),

    .write_data(32'd0),

    .read_data1(read_data1),
    .read_data2(read_data2)

);

endmodule

tb/tb_pipeline_processor.v
`timescale 1ns/1ps

module tb_pipeline_processor;

reg clk;
reg reset;

pipeline_processor uut(

.clk(clk),
.reset(reset)

);

always #5 clk=~clk;

initial begin

    $dumpfile("waveforms/pipeline.vcd");
    $dumpvars(0, tb_pipeline_processor);

    clk = 0;
    reset = 1;

    #10;
    reset = 0;

    #80;

    $finish;

end

always @(posedge clk)

begin

$display("--------------------------------");

$display("PC          = %d",uut.pc);

$display("Instruction = %h",uut.instruction);

$display("IF/ID PC    = %d",uut.ifid_pc);

$display("IF/ID INST  = %h",uut.ifid_instruction);

end

endmodule

waveforms/pipeline.vcd
$date
	Sun Jul 26 11:20:46 2026
$end
$version
	Icarus Verilog
$end
$timescale
	1ps
$end
$scope module tb_pipeline_processor $end
$var reg 1 ! clk $end
$var reg 1 " reset $end
$scope module uut $end
$var wire 1 ! clk $end
$var wire 1 " reset $end
$var wire 32 # read_data2 [31:0] $end
$var wire 32 $ read_data1 [31:0] $end
$var wire 32 % pc_next [31:0] $end
$var wire 32 & pc [31:0] $end
$var wire 32 ' instruction [31:0] $end
$var wire 32 ( ifid_pc [31:0] $end
$var wire 32 ) ifid_instruction [31:0] $end
$var wire 1 * RegWrite $end
$var wire 1 + MemtoReg $end
$var wire 1 , MemWrite $end
$var wire 1 - MemRead $end
$var wire 1 . ALUSrc $end
$var wire 2 / ALUOp [1:0] $end
$scope module CU $end
$var wire 7 0 opcode [6:0] $end
$var reg 2 1 ALUOp [1:0] $end
$var reg 1 . ALUSrc $end
$var reg 1 - MemRead $end
$var reg 1 , MemWrite $end
$var reg 1 + MemtoReg $end
$var reg 1 * RegWrite $end
$upscope $end
$scope module IF_ID $end
$var wire 1 ! clk $end
$var wire 1 " reset $end
$var wire 32 2 pc_in [31:0] $end
$var wire 32 3 instruction_in [31:0] $end
$var reg 32 4 instruction_out [31:0] $end
$var reg 32 5 pc_out [31:0] $end
$upscope $end
$scope module IM $end
$var wire 32 6 instruction [31:0] $end
$var wire 32 7 address [31:0] $end
$upscope $end
$scope module PC $end
$var wire 1 ! clk $end
$var wire 32 8 pc_next [31:0] $end
$var wire 1 " reset $end
$var reg 32 9 pc [31:0] $end
$upscope $end
$scope module RF $end
$var wire 1 ! clk $end
$var wire 5 : rd [4:0] $end
$var wire 32 ; read_data1 [31:0] $end
$var wire 32 < read_data2 [31:0] $end
$var wire 5 = rs1 [4:0] $end
$var wire 5 > rs2 [4:0] $end
$var wire 1 ? we $end
$var wire 32 @ write_data [31:0] $end
$var integer 32 A i [31:0] $end
$upscope $end
$upscope $end
$upscope $end
$enddefinitions $end
#0
$dumpvars
b100000 A
b0 @
0?
b0 >
b0 =
b0 <
b0 ;
b0 :
b0 9
b100 8
b0 7
b1000001000000110110011 6
b0 5
b0 4
b1000001000000110110011 3
b0 2
b0 1
b0 0
b0 /
0.
0-
0,
0+
0*
b0 )
b0 (
b1000001000000110110011 '
b0 &
b100 %
b0 $
b0 #
1"
0!
$end
#5000
1!
#10000
0!
0"
#15000
b10 /
b10 1
1*
b1000000000100011000001000110011 '
b1000000000100011000001000110011 3
b1000000000100011000001000110011 6
b10 >
b1 =
b110011 0
b1000 %
b1000 8
b100 &
b100 2
b100 7
b100 9
b1000001000000110110011 )
b1000001000000110110011 4
1!
#20000
0!
#25000
b1 >
b11 =
b10000011111001010110011 '
b10000011111001010110011 3
b10000011111001010110011 6
b1000000000100011000001000110011 )
b1000000000100011000001000110011 4
b100 (
b100 5
b1100 %
b1100 8
b1000 &
b1000 2
b1000 7
b1000 9
1!
#30000
0!
#35000
b1000101110001100110011 '
b1000101110001100110011 3
b1000101110001100110011 6
b100 >
b10000 %
b10000 8
b1100 &
b1100 2
b1100 7
b1100 9
b10000011111001010110011 )
b10000011111001010110011 4
b1000 (
b1000 5
1!
#40000
0!
#45000
b10 >
b101 =
bx '
bx 3
bx 6
b1000101110001100110011 )
b1000101110001100110011 4
b1100 (
b1100 5
b10100 %
b10100 8
b10000 &
b10000 2
b10000 7
b10000 9
1!
#50000
0!
#55000
b0 /
b0 1
0*
bx #
bx <
bx >
bx $
bx ;
bx =
bx 0
b11000 %
b11000 8
b10100 &
b10100 2
b10100 7
b10100 9
bx )
bx 4
b10000 (
b10000 5
1!
#60000
0!
#65000
b10100 (
b10100 5
b11100 %
b11100 8
b11000 &
b11000 2
b11000 7
b11000 9
1!
#70000
0!
#75000
b100000 %
b100000 8
b11100 &
b11100 2
b11100 7
b11100 9
b11000 (
b11000 5
1!
#80000
0!
#85000
b11100 (
b11100 5
b100100 %
b100100 8
b100000 &
b100000 2
b100000 7
b100000 9
1!
